{
  "dateRange": "Last 60 Days",
  "scrapeTime": "2026-04-20T21:29:23.890Z",
  "meta": {
    "campaigns": {
      "headers": {
        "name": "Name",
        "delivery": "Delivery",
        "budget": "Budget",
        "amount_spent": "Amount Spent",
        "clicks": "Clicks (All)",
        "lead_generated": "Lead",
        "cost_per_lead_generated": "Cost per Lead",
        "custom_event_1": "Application Submitted",
        "cost_per_custom_event_1": "Cost per Application Submitted",
        "custom_event_20": "Application Score",
        "custom_event_21": "Application Expected Value",
        "custom_event_21_amount": "Application Expected Value Value",
        "custom_event_22": "Personal or Business Loan",
        "m_avg_application_score": "Avg Application Score",
        "m_expected_roas": "Expected ROAS",
        "m_avg_expected_value": "Avg Expected Value"
      },
      "rows": [
        {
          "id": "3377699811000897",
          "cells": {
            "ag-Grid-SelectionColumn": "",
            "name": "THMC_Meta_Generic_20260206",
            "_platform_url": "https://adsmanager.facebook.com/adsmanager/manage/campaigns?act=850448857515247&filter_set=SEARCH_BY_CAMPAIGN_GROUP_ID-STRING%1EEQUAL%1E%22120239432523620031%22&selected_campaign_ids=120239432523620031",
            "delivery": "Active",
            "budget": "Using Adset Budget",
            "amount_spent": "$4,244.18",
            "clicks": "2,519",
            "lead_generated": "257.458",
            "cost_per_lead_generated": "$16.48",
            "custom_event_1": "40.958",
            "cost_per_custom_event_1": "$103.62",
            "custom_event_20": "39.958",
            "custom_event_21": "39.958",
            "custom_event_21_amount": "$217,397.29",
            "custom_event_22": "1",
            "m_avg_application_score": "61.378",
            "m_expected_roas": "51.222",
            "m_avg_expected_value": "$5,440.63"
          }
        },
        {
          "id": "3377699818000368",
          "cells": {
            "ag-Grid-SelectionColumn": "",
            "name": "THMC_Meta_Generic_20260313",
            "_platform_url": "https://adsmanager.facebook.com/adsmanager/manage/campaigns?act=850448857515247&filter_set=SEARCH_BY_CAMPAIGN_GROUP_ID-STRING%1EEQUAL%1E%22120240918657590031%22&selected_campaign_ids=120240918657590031",
            "delivery": "Active",
            "budget": "Using Adset Budget",
            "amount_spent": "$1,191.17",
            "clicks": "318",
            "lead_generated": "34",
            "cost_per_lead_generated": "$35.03",
            "custom_event_1": "3.75",
            "cost_per_custom_event_1": "$317.65",
            "custom_event_20": "3.75",
            "custom_event_21": "3.75",
            "custom_event_21_amount": "$2,933.40",
            "custom_event_22": "-",
            "m_avg_application_score": "57.8",
            "m_expected_roas": "2.463",
            "m_avg_expected_value": "$782.24"
          }
        },
        {
          "id": "3377699820000065",
          "cells": {
            "ag-Grid-SelectionColumn": "",
            "name": "THMC_Meta_Generic_20260318_RIQ",
            "_platform_url": "https://adsmanager.facebook.com/adsmanager/manage/campaigns?act=850448857515247&filter_set=SEARCH_BY_CAMPAIGN_GROUP_ID-STRING%1EEQUAL%1E%22120241096252470031%22&selected_campaign_ids=120241096252470031",
            "delivery": "Active",
            "budget": "Using Adset Budget",
            "amount_spent": "$838.32",
            "clicks": "292",
            "lead_generated": "24.25",
            "cost_per_lead_generated": "$34.57",
            "custom_event_1": "2.25",
            "cost_per_custom_event_1": "$372.59",
            "custom_event_20": "2.25",
            "custom_event_21": "2.25",
            "custom_event_21_amount": "$3,593.50",
            "custom_event_22": "-",
            "m_avg_application_score": "67.667",
            "m_expected_roas": "4.287",
            "m_avg_expected_value": "$1,597.11"
          }
        },
        {
          "id": "4503599720000067",
          "cells": {
            "ag-Grid-SelectionColumn": "",
            "name": "THMC_Meta_Brokers_20260304 _Angle_Test",
            "_platform_url": "https://adsmanager.facebook.com/adsmanager/manage/campaigns?act=850448857515247&filter_set=SEARCH_BY_CAMPAIGN_GROUP_ID-STRING%1EEQUAL%1E%22120240548660790031%22&selected_campaign_ids=120240548660790031",
            "delivery": "Active",
            "budget": "Using Adset Budget",
            "amount_spent": "$1,505.42",
            "clicks": "421",
            "lead_generated": "55.833",
            "cost_per_lead_generated": "$26.96",
            "custom_event_1": "6",
            "cost_per_custom_event_1": "$250.90",
            "custom_event_20": "4",
            "custom_event_21": "4",
            "custom_event_21_amount": "$31,872.19",
            "custom_event_22": "-",
            "m_avg_application_score": "63.25",
            "m_expected_roas": "21.172",
            "m_avg_expected_value": "$7,968.05"
          }
        },
        {
          "id": "3377699808000188",
          "cells": {
            "ag-Grid-SelectionColumn": "",
            "name": "THMC_Meta_Forecasa&ForecasaADV+",
            "_platform_url": "https://adsmanager.facebook.com/adsmanager/manage/campaigns?act=850448857515247&filter_set=SEARCH_BY_CAMPAIGN_GROUP_ID-STRING%1EEQUAL%1E%22120238051629060031%22&selected_campaign_ids=120238051629060031",
            "delivery": "Paused",
            "budget": "$40.00\n(daily)",
            "amount_spent": "-",
            "clicks": "-",
            "lead_generated": "-",
            "cost_per_lead_generated": "-",
            "custom_event_1": "-",
            "cost_per_custom_event_1": "-",
            "custom_event_20": "-",
            "custom_event_21": "-",
            "custom_event_21_amount": "$0.00",
            "custom_event_22": "-",
            "m_avg_application_score": "-",
            "m_expected_roas": "-",
            "m_avg_expected_value": "-"
          }
        },
        {
          "id": "3377699808000368",
          "cells": {
            "ag-Grid-SelectionColumn": "",
            "name": "THMC_Meta_Milwaukee_20260106",
            "_platform_url": "https://adsmanager.facebook.com/adsmanager/manage/campaigns?act=850448857515247&filter_set=SEARCH_BY_CAMPAIGN_GROUP_ID-STRING%1EEQUAL%1E%22120238329184250031%22&selected_campaign_ids=120238329184250031",
            "delivery": "Paused",
            "budget": "$50.00\n(daily)",
            "amount_spent": "-",
            "clicks": "-",
            "lead_generated": "-",
            "cost_per_lead_generated": "-",
            "custom_event_1": "-",
            "cost_per_custom_event_1": "-",
            "custom_event_20": "-",
            "custom_event_21": "-",
            "custom_event_21_amount": "$0.00",
            "custom_event_22": "-",
            "m_avg_application_score": "-",
            "m_expected_roas": "-",
            "m_avg_expected_value": "-"
          }
        },
        {
          "id": "3377699818000367",
          "cells": {
            "ag-Grid-SelectionColumn": "",
            "name": "THMC_Meta_Generic_20251110_Copy_ABO",
            "_platform_url": "https://adsmanager.facebook.com/adsmanager/manage/campaigns?act=850448857515247&filter_set=SEARCH_BY_CAMPAIGN_GROUP_ID-STRING%1EEQUAL%1E%22120240919013850031%22&selected_campaign_ids=120240919013850031",
            "delivery": "Paused",
            "budget": "Using Adset Budget",
            "amount_spent": "$19.88",
            "clicks": "9",
            "lead_generated": "0.5",
            "cost_per_lead_generated": "$39.76",
            "custom_event_1": "-",
            "cost_per_custom_event_1": "-",
            "custom_event_20": "-",
            "custom_event_21": "-",
            "custom_event_21_amount": "-",
            "custom_event_22": "-",
            "m_avg_application_score": "-",
            "m_expected_roas": "-",
            "m_avg_expected_value": "-"
          }
        },
        {
          "id": "4503599706000234",
          "cells": {
            "ag-Grid-SelectionColumn": "",
            "name": "THMC_Meta_Generic_20251110",
            "_platform_url": "https://adsmanager.facebook.com/adsmanager/manage/campaigns?act=850448857515247&filter_set=SEARCH_BY_CAMPAIGN_GROUP_ID-STRING%1EEQUAL%1E%22120235243629020031%22&selected_campaign_ids=120235243629020031",
            "delivery": "Paused",
            "budget": "$315.00\n(daily)",
            "amount_spent": "-",
            "clicks": "-",
            "lead_generated": "0.667",
            "cost_per_lead_generated": "-",
            "custom_event_1": "0.143",
            "cost_per_custom_event_1": "-",
            "custom_event_20": "0.143",
            "custom_event_21": "0.143",
            "custom_event_21_amount": "$398.39",
            "custom_event_22": "-",
            "m_avg_application_score": "61.981",
            "m_expected_roas": "-",
            "m_avg_expected_value": "$2,787.89"
          }
        },
        {
          "id": "4503599713000291",
          "cells": {
            "ag-Grid-SelectionColumn": "",
            "name": "THMC_Meta_Generic_20251110 - Copy (RIQ Flippers)",
            "_platform_url": "https://adsmanager.facebook.com/adsmanager/manage/campaigns?act=850448857515247&filter_set=SEARCH_BY_CAMPAIGN_GROUP_ID-STRING%1EEQUAL%1E%22120238730003590031%22&selected_campaign_ids=120238730003590031",
            "delivery": "Paused",
            "budget": "$100.00\n(daily)",
            "amount_spent": "-",
            "clicks": "-",
            "lead_generated": "-",
            "cost_per_lead_generated": "-",
            "custom_event_1": "-",
            "cost_per_custom_event_1": "-",
            "custom_event_20": "-",
            "custom_event_21": "-",
            "custom_event_21_amount": "$0.00",
            "custom_event_22": "-",
            "m_avg_application_score": "-",
            "m_expected_roas": "-",
            "m_avg_expected_value": "-"
          }
        },
        {
          "id": "4503599713000335",
          "cells": {
            "ag-Grid-SelectionColumn": "",
            "name": "THMC_Meta_Brokers_20260106 - Copy(RIQAgents+LO's)",
            "_platform_url": "https://adsmanager.facebook.com/adsmanager/manage/campaigns?act=850448857515247&filter_set=SEARCH_BY_CAMPAIGN_GROUP_ID-STRING%1EEQUAL%1E%22120238771546440031%22&selected_campaign_ids=120238771546440031",
            "delivery": "Paused",
            "budget": "$100.00\n(daily)",
            "amount_spent": "-",
            "clicks": "-",
            "lead_generated": "-",
            "cost_per_lead_generated": "-",
            "custom_event_1": "-",
            "cost_per_custom_event_1": "-",
            "custom_event_20": "-",
            "custom_event_21": "-",
            "custom_event_21_amount": "$0.00",
            "custom_event_22": "-",
            "m_avg_application_score": "-",
            "m_expected_roas": "-",
            "m_avg_expected_value": "-"
          }
        },
        {
          "id": "Totals",
          "cells": {
            "ag-Grid-SelectionColumn": "",
            "name": "Totals",
            "delivery": "",
            "budget": "",
            "amount_spent": "$7,798.97",
            "clicks": "3,559",
            "lead_generated": "372.708",
            "cost_per_lead_generated": "$20.93",
            "custom_event_1": "53.101",
            "cost_per_custom_event_1": "$146.87",
            "custom_event_20": "50.101",
            "custom_event_21": "50.101",
            "custom_event_21_amount": "$256,194.77",
            "custom_event_22": "1",
            "m_avg_application_score": "61.544",
            "m_expected_roas": "32.85",
            "m_avg_expected_value": "$5,113.57"
          }
        }
      ]
    },
    "adsets": {
      "headers": {
        "name": "Name",
        "custom_event_1": "Application Submitted",
        "cost_per_custom_event_1": "Cost per Application Submitted",
        "custom_event_20": "Application Score",
        "delivery": "Delivery",
        "budget": "Budget",
        "amount_spent": "Amount Spent",
        "clicks": "Clicks (All)",
        "lead_generated": "Lead",
        "cost_per_lead_generated": "Cost per Lead",
        "custom_event_21": "Application Expected Value",
        "custom_event_21_amount": "Application Expected Value Value",
        "custom_event_22": "Personal or Business Loan",
        "ad_schedule": "Ad Schedule",
        "m_avg_application_score": "Avg Application Score",
        "m_expected_roas": "Expected ROAS",
        "m_avg_expected_value": "Avg Expected Value"
      },
      "rows": [
        {
          "id": "3377699819000555",
          "cells": {
            "ag-Grid-SelectionColumn": "",
            "name": "Broad_Forms_Under_Contract_Emma_No_Caps",
            "_platform_url": "https://adsmanager.facebook.com/adsmanager/manage/adsets?act=850448857515247&filter_set=SEARCH_BY_CAMPAIGN_ID-STRING%1EEQUAL%1E%22120240911215300031%22&selected_adset_ids=120240911215300031",
            "delivery": "Active",
            "budget": "$50.00\n(daily)",
            "amount_spent": "$567.61",
            "clicks": "432",
            "lead_generated": "55.5",
            "cost_per_lead_generated": "$10.23",
            "custom_event_1": "8",
            "cost_per_custom_event_1": "$70.95",
            "custom_event_20": "8",
            "custom_event_21": "8",
            "custom_event_21_amount": "$13,268.81",
            "custom_event_22": "1",
            "ad_schedule": "Mar 13th, 2026 - Ongoing",
            "m_avg_application_score": "62.751",
            "m_expected_roas": "23.377",
            "m_avg_expected_value": "$1,658.62"
          }
        },
        {
          "id": "3377699824000486",
          "cells": {
            "ag-Grid-SelectionColumn": "",
            "name": "Broad_Form_Explainer_9:16_30sec",
            "_platform_url": "https://adsmanager.facebook.com/adsmanager/manage/adsets?act=850448857515247&filter_set=SEARCH_BY_CAMPAIGN_ID-STRING%1EEQUAL%1E%22120242186731040031%22&selected_adset_ids=120242186731040031",
            "delivery": "Active",
            "budget": "$30.00\n(daily)",
            "amount_spent": "$327.31",
            "clicks": "53",
            "lead_generated": "5.25",
            "cost_per_lead_generated": "$62.34",
            "custom_event_1": "-",
            "cost_per_custom_event_1": "-",
            "custom_event_20": "-",
            "custom_event_21": "-",
            "custom_event_21_amount": "-",
            "custom_event_22": "-",
            "ad_schedule": "Apr 9th, 2026 - Ongoing",
            "m_avg_application_score": "-",
            "m_expected_roas": "-",
            "m_avg_expected_value": "-"
          }
        },
        {
          "id": "3377699824000487",
          "cells": {
            "ag-Grid-SelectionColumn": "",
            "name": "Broad_Forms_FdUp_Short",
            "_platform_url": "https://adsmanager.facebook.com/adsmanager/manage/adsets?act=850448857515247&filter_set=SEARCH_BY_CAMPAIGN_ID-STRING%1EEQUAL%1E%22120242186503670031%22&selected_adset_ids=120242186503670031",
            "delivery": "Active",
            "budget": "$30.00\n(daily)",
            "amount_spent": "$333.95",
            "clicks": "141",
            "lead_generated": "18.5",
            "cost_per_lead_generated": "$18.05",
            "custom_event_1": "2",
            "cost_per_custom_event_1": "$166.98",
            "custom_event_20": "2",
            "custom_event_21": "2",
            "custom_event_21_amount": "$1,675.60",
            "custom_event_22": "-",
            "ad_schedule": "Apr 9th, 2026 - Ongoing",
            "m_avg_application_score": "64.5",
            "m_expected_roas": "5.018",
            "m_avg_expected_value": "$837.80"
          }
        },
        {
          "id": "4503599723000219",
          "cells": {
            "ag-Grid-SelectionColumn": "",
            "name": "Broad_Forms_Distressed_Asset",
            "_platform_url": "https://adsmanager.facebook.com/adsmanager/manage/adsets?act=850448857515247&filter_set=SEARCH_BY_CAMPAIGN_ID-STRING%1EEQUAL%1E%22120240548660800031%22&selected_adset_ids=120240548660800031",
            "delivery": "Active",
            "budget": "$50.00\n(daily)",
            "amount_spent": "$646.52",
            "clicks": "234",
            "lead_generated": "36.833",
            "cost_per_lead_generated": "$17.55",
            "custom_event_1": "3",
            "cost_per_custom_event_1": "$215.51",
            "custom_event_20": "1",
            "custom_event_21": "1",
            "custom_event_21_amount": "$116.15",
            "custom_event_22": "-",
            "ad_schedule": "Mar 4th, 2026 - Ongoing",
            "m_avg_application_score": "52",
            "m_expected_roas": "0.18",
            "m_avg_expected_value": "$116.15"
          }
        },
        {
          "id": "4503599724000457",
          "cells": {
            "ag-Grid-SelectionColumn": "",
            "name": "Broad_Forms_Under_Contract_Emma_Caps",
            "_platform_url": "https://adsmanager.facebook.com/adsmanager/manage/adsets?act=850448857515247&filter_set=SEARCH_BY_CAMPAIGN_ID-STRING%1EEQUAL%1E%22120240910588080031%22&selected_adset_ids=120240910588080031",
            "delivery": "Active",
            "budget": "$50.00\n(daily)",
            "amount_spent": "$566.93",
            "clicks": "470",
            "lead_generated": "65",
            "cost_per_lead_generated": "$8.72",
            "custom_event_1": "8.667",
            "cost_per_custom_event_1": "$65.42",
            "custom_event_20": "8.667",
            "custom_event_21": "8.667",
            "custom_event_21_amount": "$16,079.81",
            "custom_event_22": "-",
            "ad_schedule": "Mar 13th, 2026 - Ongoing",
            "m_avg_application_score": "63.154",
            "m_expected_roas": "28.363",
            "m_avg_expected_value": "$1,855.38"
          }
        },
        {
          "id": "4503599727000399",
          "cells": {
            "ag-Grid-SelectionColumn": "",
            "name": "Broad_Forms_Experienced_Emma",
            "_platform_url": "https://adsmanager.facebook.com/adsmanager/manage/adsets?act=850448857515247&filter_set=SEARCH_BY_CAMPAIGN_ID-STRING%1EEQUAL%1E%22120241515304800031%22&selected_adset_ids=120241515304800031",
            "delivery": "Active",
            "budget": "$55.00\n(daily)",
            "amount_spent": "$754.63",
            "clicks": "538",
            "lead_generated": "36",
            "cost_per_lead_generated": "$20.96",
            "custom_event_1": "8.333",
            "cost_per_custom_event_1": "$90.56",
            "custom_event_20": "8.333",
            "custom_event_21": "8.333",
            "custom_event_21_amount": "$147,813.19",
            "custom_event_22": "-",
            "ad_schedule": "Mar 27th, 2026 - Ongoing",
            "m_avg_application_score": "62",
            "m_expected_roas": "195.875",
            "m_avg_expected_value": "$17,737.65"
          }
        },
        {
          "id": "4503599728000480",
          "cells": {
            "ag-Grid-SelectionColumn": "",
            "name": "Broad_Forms_FdUp",
            "_platform_url": "https://adsmanager.facebook.com/adsmanager/manage/adsets?act=850448857515247&filter_set=SEARCH_BY_CAMPAIGN_ID-STRING%1EEQUAL%1E%22120241939706090031%22&selected_adset_ids=120241939706090031",
            "delivery": "Active",
            "budget": "$32.00\n(daily)",
            "amount_spent": "$428.95",
            "clicks": "196",
            "lead_generated": "13.5",
            "cost_per_lead_generated": "$31.77",
            "custom_event_1": "4.5",
            "cost_per_custom_event_1": "$95.32",
            "custom_event_20": "4.5",
            "custom_event_21": "4.5",
            "custom_event_21_amount": "$13,585.17",
            "custom_event_22": "-",
            "ad_schedule": "Apr 3rd, 2026 - Ongoing",
            "m_avg_application_score": "54.444",
            "m_expected_roas": "31.671",
            "m_avg_expected_value": "$3,018.93"
          }
        },
        {
          "id": "4503599729000177",
          "cells": {
            "ag-Grid-SelectionColumn": "",
            "name": "Broad_Form_Selfie_Style_AI",
            "_platform_url": "https://adsmanager.facebook.com/adsmanager/manage/adsets?act=850448857515247&filter_set=SEARCH_BY_CAMPAIGN_ID-STRING%1EEQUAL%1E%22120242085807140031%22&selected_adset_ids=120242085807140031",
            "delivery": "Active",
            "budget": "$30.00\n(daily)",
            "amount_spent": "$391.13",
            "clicks": "115",
            "lead_generated": "14",
            "cost_per_lead_generated": "$27.94",
            "custom_event_1": "1",
            "cost_per_custom_event_1": "$391.13",
            "custom_event_20": "1",
            "custom_event_21": "1",
            "custom_event_21_amount": "$165.07",
            "custom_event_22": "-",
            "ad_schedule": "Apr 7th, 2026 - Ongoing",
            "m_avg_application_score": "51",
            "m_expected_roas": "0.422",
            "m_avg_expected_value": "$165.07"
          }
        },
        {
          "id": "4503599729000271",
          "cells": {
            "ag-Grid-SelectionColumn": "",
            "name": "Broad_Forms_Emma_In_House",
            "_platform_url": "https://adsmanager.facebook.com/adsmanager/manage/adsets?act=850448857515247&filter_set=SEARCH_BY_CAMPAIGN_ID-STRING%1EEQUAL%1E%22120242145105080031%22&selected_adset_ids=120242145105080031",
            "delivery": "Active",
            "budget": "$30.00\n(daily)",
            "amount_spent": "$354.32",
            "clicks": "285",
            "lead_generated": "23.458",
            "cost_per_lead_generated": "$15.10",
            "custom_event_1": "3.458",
            "cost_per_custom_event_1": "$102.45",
            "custom_event_20": "3.458",
            "custom_event_21": "3.458",
            "custom_event_21_amount": "$21,990.79",
            "custom_event_22": "-",
            "ad_schedule": "Apr 8th, 2026 - Ongoing",
            "m_avg_application_score": "56.543",
            "m_expected_roas": "62.065",
            "m_avg_expected_value": "$6,358.85"
          }
        },
        {
          "id": "4503599730000212",
          "cells": {
            "ag-Grid-SelectionColumn": "",
            "name": "THMC_RipCorner_Static_20260410",
            "_platform_url": "https://adsmanager.facebook.com/adsmanager/manage/adsets?act=850448857515247&filter_set=SEARCH_BY_CAMPAIGN_ID-STRING%1EEQUAL%1E%22120242234014210031%22&selected_adset_ids=120242234014210031",
            "delivery": "Active",
            "budget": "$60.00\n(daily)",
            "amount_spent": "$481.64",
            "clicks": "110",
            "lead_generated": "15",
            "cost_per_lead_generated": "$32.11",
            "custom_event_1": "3",
            "cost_per_custom_event_1": "$160.55",
            "custom_event_20": "3",
            "custom_event_21": "3",
            "custom_event_21_amount": "$31,756.04",
            "custom_event_22": "-",
            "ad_schedule": "Apr 10th, 2026 - Ongoing",
            "m_avg_application_score": "67",
            "m_expected_roas": "65.933",
            "m_avg_expected_value": "$10,585.35"
          }
        },
        {
          "id": "3377699809000331",
          "cells": {
            "ag-Grid-SelectionColumn": "",
            "name": "THMC_Meta_Forecasa_Site+forms",
            "_platform_url": "https://adsmanager.facebook.com/adsmanager/manage/adsets?act=850448857515247&filter_set=SEARCH_BY_CAMPAIGN_ID-STRING%1EEQUAL%1E%22120238051629130031%22&selected_adset_ids=120238051629130031",
            "delivery": "Campaign Paused",
            "budget": "Using Campaign Budget",
            "amount_spent": "-",
            "clicks": "-",
            "lead_generated": "-",
            "cost_per_lead_generated": "-",
            "custom_event_1": "-",
            "cost_per_custom_event_1": "-",
            "custom_event_20": "-",
            "custom_event_21": "-",
            "custom_event_21_amount": "$0.00",
            "custom_event_22": "-",
            "ad_schedule": "Dec 29th, 2025 - Ongoing",
            "m_avg_application_score": "-",
            "m_expected_roas": "-",
            "m_avg_expected_value": "-"
          }
        },
        {
          "id": "3377699811000060",
          "cells": {
            "ag-Grid-SelectionColumn": "",
            "name": "THMC_Generic_20251110_RIQ_Flippers_1.19.26 - Copy (Adv+)",
            "_platform_url": "https://adsmanager.facebook.com/adsmanager/manage/adsets?act=850448857515247&filter_set=SEARCH_BY_CAMPAIGN_ID-STRING%1EEQUAL%1E%22120238822157600031%22&selected_adset_ids=120238822157600031",
            "delivery": "Campaign Paused",
            "budget": "Using Campaign Budget",
            "amount_spent": "-",
            "clicks": "-",
            "lead_generated": "-",
            "cost_per_lead_generated": "-",
            "custom_event_1": "-",
            "cost_per_custom_event_1": "-",
            "custom_event_20": "-",
            "custom_event_21": "-",
            "custom_event_21_amount": "$0.00",
            "custom_event_22": "-",
            "ad_schedule": "Jan 19th, 2026 - Ongoing",
            "m_avg_application_score": "-",
            "m_expected_roas": "-",
            "m_avg_expected_value": "-"
          }
        },
        {
          "id": "3377699811000302",
          "cells": {
            "ag-Grid-SelectionColumn": "",
            "name": "RIQ_Adv+_Brokers",
            "_platform_url": "https://adsmanager.facebook.com/adsmanager/manage/adsets?act=850448857515247&filter_set=SEARCH_BY_CAMPAIGN_ID-STRING%1EEQUAL%1E%22120238888168540031%22&selected_adset_ids=120238888168540031",
            "delivery": "Campaign Paused",
            "budget": "Using Campaign Budget",
            "amount_spent": "-",
            "clicks": "-",
            "lead_generated": "-",
            "cost_per_lead_generated": "-",
            "custom_event_1": "-",
            "cost_per_custom_event_1": "-",
            "custom_event_20": "-",
            "custom_event_21": "-",
            "custom_event_21_amount": "$0.00",
            "custom_event_22": "-",
            "ad_schedule": "Jan 21st, 2026 - Ongoing",
            "m_avg_application_score": "-",
            "m_expected_roas": "-",
            "m_avg_expected_value": "-"
          }
        },
        {
          "id": "4503599709000653",
          "cells": {
            "ag-Grid-SelectionColumn": "",
            "name": "THMC_Generic_20251110_BROAD",
            "_platform_url": "https://adsmanager.facebook.com/adsmanager/manage/adsets?act=850448857515247&filter_set=SEARCH_BY_CAMPAIGN_ID-STRING%1EEQUAL%1E%22120235243629040031%22&selected_adset_ids=120235243629040031",
            "delivery": "Campaign Paused",
            "budget": "Using Campaign Budget",
            "amount_spent": "-",
            "clicks": "-",
            "lead_generated": "0.667",
            "cost_per_lead_generated": "-",
            "custom_event_1": "0.143",
            "cost_per_custom_event_1": "-",
            "custom_event_20": "0.143",
            "custom_event_21": "0.143",
            "custom_event_21_amount": "$398.39",
            "custom_event_22": "-",
            "ad_schedule": "Nov 11th, 2025 - Ongoing",
            "m_avg_application_score": "61.981",
            "m_expected_roas": "-",
            "m_avg_expected_value": "$2,787.89"
          }
        },
        {
          "id": "3377699809000928",
          "cells": {
            "ag-Grid-SelectionColumn": "",
            "name": "THMC_Meta_MKE_Scott_Videos_BROAD",
            "_platform_url": "https://adsmanager.facebook.com/adsmanager/manage/adsets?act=850448857515247&filter_set=SEARCH_BY_CAMPAIGN_ID-STRING%1EEQUAL%1E%22120238329184240031%22&selected_adset_ids=120238329184240031",
            "delivery": "Paused",
            "budget": "Using Campaign Budget",
            "amount_spent": "-",
            "clicks": "-",
            "lead_generated": "-",
            "cost_per_lead_generated": "-",
            "custom_event_1": "-",
            "cost_per_custom_event_1": "-",
            "custom_event_20": "-",
            "custom_event_21": "-",
            "custom_event_21_amount": "$0.00",
            "custom_event_22": "-",
            "ad_schedule": "Jan 6th, 2026 - Ongoing",
            "m_avg_application_score": "-",
            "m_expected_roas": "-",
            "m_avg_expected_value": "-"
          }
        },
        {
          "id": "3377699819000599",
          "cells": {
            "ag-Grid-SelectionColumn": "",
            "name": "Broad_Form_Videos",
            "_platform_url": "https://adsmanager.facebook.com/adsmanager/manage/adsets?act=850448857515247&filter_set=SEARCH_BY_CAMPAIGN_ID-STRING%1EEQUAL%1E%22120240919013830031%22&selected_adset_ids=120240919013830031",
            "delivery": "Paused",
            "budget": "$30.00\n(daily)",
            "amount_spent": "$19.88",
            "clicks": "9",
            "lead_generated": "0.5",
            "cost_per_lead_generated": "$39.76",
            "custom_event_1": "-",
            "cost_per_custom_event_1": "-",
            "custom_event_20": "-",
            "custom_event_21": "-",
            "custom_event_21_amount": "-",
            "custom_event_22": "-",
            "ad_schedule": "Mar 13th, 2026 - Ongoing",
            "m_avg_application_score": "-",
            "m_expected_roas": "-",
            "m_avg_expected_value": "-"
          }
        },
        {
          "id": "3377699819000600",
          "cells": {
            "ag-Grid-SelectionColumn": "",
            "name": "Broad_Form_iphone",
            "_platform_url": "https://adsmanager.facebook.com/adsmanager/manage/adsets?act=850448857515247&filter_set=SEARCH_BY_CAMPAIGN_ID-STRING%1EEQUAL%1E%22120240918657600031%22&selected_adset_ids=120240918657600031",
            "delivery": "Paused",
            "budget": "$43.00\n(daily)",
            "amount_spent": "$159.99",
            "clicks": "56",
            "lead_generated": "7",
            "cost_per_lead_generated": "$22.86",
            "custom_event_1": "1",
            "cost_per_custom_event_1": "$159.99",
            "custom_event_20": "1",
            "custom_event_21": "1",
            "custom_event_21_amount": "$608.62",
            "custom_event_22": "-",
            "ad_schedule": "Mar 13th, 2026 - Ongoing",
            "m_avg_application_score": "59",
            "m_expected_roas": "3.804",
            "m_avg_expected_value": "$608.62"
          }
        },
        {
          "id": "3377699821000390",
          "cells": {
            "ag-Grid-SelectionColumn": "",
            "name": "Broad_Forms_WeKnowFlips_Emma_Video",
            "_platform_url": "https://adsmanager.facebook.com/adsmanager/manage/adsets?act=850448857515247&filter_set=SEARCH_BY_CAMPAIGN_ID-STRING%1EEQUAL%1E%22120241203249180031%22&selected_adset_ids=120241203249180031",
            "delivery": "Paused",
            "budget": "$36.00\n(daily)",
            "amount_spent": "$128.99",
            "clicks": "48",
            "lead_generated": "6",
            "cost_per_lead_generated": "$21.50",
            "custom_event_1": "1",
            "cost_per_custom_event_1": "$128.99",
            "custom_event_20": "-",
            "custom_event_21": "-",
            "custom_event_21_amount": "-",
            "custom_event_22": "-",
            "ad_schedule": "Mar 20th, 2026 - Ongoing",
            "m_avg_application_score": "-",
            "m_expected_roas": "-",
            "m_avg_expected_value": "-"
          }
        },
        {
          "id": "3377699824000069",
          "cells": {
            "ag-Grid-SelectionColumn": "",
            "name": "Broad_Form_IG_LE",
            "_platform_url": "https://adsmanager.facebook.com/adsmanager/manage/adsets?act=850448857515247&filter_set=SEARCH_BY_CAMPAIGN_ID-STRING%1EEQUAL%1E%22120242048415300031%22&selected_adset_ids=120242048415300031",
            "delivery": "Paused",
            "budget": "$40.00\n(daily)",
            "amount_spent": "$427.72",
            "clicks": "121",
            "lead_generated": "7.25",
            "cost_per_lead_generated": "$59.00",
            "custom_event_1": "0.25",
            "cost_per_custom_event_1": "$1,710.88",
            "custom_event_20": "0.25",
            "custom_event_21": "0.25",
            "custom_event_21_amount": "$314.69",
            "custom_event_22": "-",
            "ad_schedule": "Apr 6th, 2026 - Ongoing",
            "m_avg_application_score": "65",
            "m_expected_roas": "0.736",
            "m_avg_expected_value": "$1,258.77"
          }
        },
        {
          "id": "4503599723000139",
          "cells": {
            "ag-Grid-SelectionColumn": "",
            "name": "Broad_Forms_&_LP_WeKnowFlips_AI_Woman",
            "_platform_url": "https://adsmanager.facebook.com/adsmanager/manage/adsets?act=850448857515247&filter_set=SEARCH_BY_CAMPAIGN_ID-STRING%1EEQUAL%1E%22120240512901880031%22&selected_adset_ids=120240512901880031",
            "delivery": "Paused",
            "budget": "$25.00\n(daily)",
            "amount_spent": "-",
            "clicks": "-",
            "lead_generated": "-",
            "cost_per_lead_generated": "-",
            "custom_event_1": "-",
            "cost_per_custom_event_1": "-",
            "custom_event_20": "-",
            "custom_event_21": "-",
            "custom_event_21_amount": "$0.00",
            "custom_event_22": "-",
            "ad_schedule": "Mar 3rd, 2026 - Ongoing",
            "m_avg_application_score": "-",
            "m_expected_roas": "-",
            "m_avg_expected_value": "-"
          }
        },
        {
          "id": "4503599723000217",
          "cells": {
            "ag-Grid-SelectionColumn": "",
            "name": "Broad_Forms_Broker_First_Lender",
            "_platform_url": "https://adsmanager.facebook.com/adsmanager/manage/adsets?act=850448857515247&filter_set=SEARCH_BY_CAMPAIGN_ID-STRING%1EEQUAL%1E%22120240548660860031%22&selected_adset_ids=120240548660860031",
            "delivery": "Paused",
            "budget": "$20.00\n(daily)",
            "amount_spent": "-",
            "clicks": "-",
            "lead_generated": "-",
            "cost_per_lead_generated": "-",
            "custom_event_1": "-",
            "cost_per_custom_event_1": "-",
            "custom_event_20": "-",
            "custom_event_21": "-",
            "custom_event_21_amount": "$0.00",
            "custom_event_22": "-",
            "ad_schedule": "Mar 4th, 2026 - Ongoing",
            "m_avg_application_score": "-",
            "m_expected_roas": "-",
            "m_avg_expected_value": "-"
          }
        },
        {
          "id": "4503599723000460",
          "cells": {
            "ag-Grid-SelectionColumn": "",
            "name": "Broad_Forms_&_LP_WeFundIt_Caps",
            "_platform_url": "https://adsmanager.facebook.com/adsmanager/manage/adsets?act=850448857515247&filter_set=SEARCH_BY_CAMPAIGN_ID-STRING%1EEQUAL%1E%22120240630527350031%22&selected_adset_ids=120240630527350031",
            "delivery": "Paused",
            "budget": "$30.00\n(daily)",
            "amount_spent": "$113.92",
            "clicks": "71",
            "lead_generated": "11.5",
            "cost_per_lead_generated": "$9.91",
            "custom_event_1": "-",
            "cost_per_custom_event_1": "-",
            "custom_event_20": "-",
            "custom_event_21": "-",
            "custom_event_21_amount": "-",
            "custom_event_22": "-",
            "ad_schedule": "Mar 6th, 2026 - Ongoing",
            "m_avg_application_score": "-",
            "m_expected_roas": "-",
            "m_avg_expected_value": "-"
          }
        },
        {
          "id": "4503599726000440",
          "cells": {
            "ag-Grid-SelectionColumn": "",
            "name": "Broad_Forms_Speed_Emma",
            "_platform_url": "https://adsmanager.facebook.com/adsmanager/manage/adsets?act=850448857515247&filter_set=SEARCH_BY_CAMPAIGN_ID-STRING%1EEQUAL%1E%22120241208925520031%22&selected_adset_ids=120241208925520031",
            "delivery": "Paused",
            "budget": "$24.00\n(daily)",
            "amount_spent": "$7.73",
            "clicks": "8",
            "lead_generated": "1",
            "cost_per_lead_generated": "$7.73",
            "custom_event_1": "-",
            "cost_per_custom_event_1": "-",
            "custom_event_20": "-",
            "custom_event_21": "-",
            "custom_event_21_amount": "-",
            "custom_event_22": "-",
            "ad_schedule": "Mar 20th, 2026 - Ongoing",
            "m_avg_application_score": "-",
            "m_expected_roas": "-",
            "m_avg_expected_value": "-"
          }
        },
        {
          "id": "4503599726000441",
          "cells": {
            "ag-Grid-SelectionColumn": "",
            "name": "Broad_Forms_Speed_AI",
            "_platform_url": "https://adsmanager.facebook.com/adsmanager/manage/adsets?act=850448857515247&filter_set=SEARCH_BY_CAMPAIGN_ID-STRING%1EEQUAL%1E%22120241208925500031%22&selected_adset_ids=120241208925500031",
            "delivery": "Paused",
            "budget": "$36.00\n(daily)",
            "amount_spent": "$477.01",
            "clicks": "183",
            "lead_generated": "13",
            "cost_per_lead_generated": "$36.69",
            "custom_event_1": "4",
            "cost_per_custom_event_1": "$119.25",
            "custom_event_20": "4",
            "custom_event_21": "4",
            "custom_event_21_amount": "$2,759.56",
            "custom_event_22": "-",
            "ad_schedule": "Mar 20th, 2026 - Ongoing",
            "m_avg_application_score": "66",
            "m_expected_roas": "5.785",
            "m_avg_expected_value": "$689.89"
          }
        },
        {
          "id": "4503599727000397",
          "cells": {
            "ag-Grid-SelectionColumn": "",
            "name": "Broad_Forms_AI_Illustrations",
            "_platform_url": "https://adsmanager.facebook.com/adsmanager/manage/adsets?act=850448857515247&filter_set=SEARCH_BY_CAMPAIGN_ID-STRING%1EEQUAL%1E%22120241516310650031%22&selected_adset_ids=120241516310650031",
            "delivery": "Paused",
            "budget": "$46.00\n(daily)",
            "amount_spent": "$484.97",
            "clicks": "143",
            "lead_generated": "13",
            "cost_per_lead_generated": "$37.31",
            "custom_event_1": "1",
            "cost_per_custom_event_1": "$484.97",
            "custom_event_20": "1",
            "custom_event_21": "1",
            "custom_event_21_amount": "$224.36",
            "custom_event_22": "-",
            "ad_schedule": "Mar 27th, 2026 - Ongoing",
            "m_avg_application_score": "53",
            "m_expected_roas": "0.463",
            "m_avg_expected_value": "$224.36"
          }
        },
        {
          "id": "4503599727000398",
          "cells": {
            "ag-Grid-SelectionColumn": "",
            "name": "Broad_Forms_Easy_Funding",
            "_platform_url": "https://adsmanager.facebook.com/adsmanager/manage/adsets?act=850448857515247&filter_set=SEARCH_BY_CAMPAIGN_ID-STRING%1EEQUAL%1E%22120241515934040031%22&selected_adset_ids=120241515934040031",
            "delivery": "Paused",
            "budget": "$30.00\n(daily)",
            "amount_spent": "$25.17",
            "clicks": "4",
            "lead_generated": "-",
            "cost_per_lead_generated": "-",
            "custom_event_1": "-",
            "cost_per_custom_event_1": "-",
            "custom_event_20": "-",
            "custom_event_21": "-",
            "custom_event_21_amount": "$0.00",
            "custom_event_22": "-",
            "ad_schedule": "Mar 27th, 2026 - Ongoing",
            "m_avg_application_score": "-",
            "m_expected_roas": "-",
            "m_avg_expected_value": "-"
          }
        },
        {
          "id": "4503599728000063",
          "cells": {
            "ag-Grid-SelectionColumn": "",
            "name": "Broad_Form_Banks_Move_Slow",
            "_platform_url": "https://adsmanager.facebook.com/adsmanager/manage/adsets?act=850448857515247&filter_set=SEARCH_BY_CAMPAIGN_ID-STRING%1EEQUAL%1E%22120241699028930031%22&selected_adset_ids=120241699028930031",
            "delivery": "Paused",
            "budget": "$30.00\n(daily)",
            "amount_spent": "$99.87",
            "clicks": "28",
            "lead_generated": "3",
            "cost_per_lead_generated": "$33.29",
            "custom_event_1": "-",
            "cost_per_custom_event_1": "-",
            "custom_event_20": "-",
            "custom_event_21": "-",
            "custom_event_21_amount": "-",
            "custom_event_22": "-",
            "ad_schedule": "Mar 30th, 2026 - Ongoing",
            "m_avg_application_score": "-",
            "m_expected_roas": "-",
            "m_avg_expected_value": "-"
          }
        },
        {
          "id": "Totals",
          "cells": {
            "ag-Grid-SelectionColumn": "",
            "name": "Totals",
            "custom_event_1": "53.101",
            "cost_per_custom_event_1": "$146.87",
            "custom_event_20": "50.101",
            "delivery": "",
            "budget": "",
            "amount_spent": "$7,798.97",
            "clicks": "3,559",
            "lead_generated": "371.708",
            "cost_per_lead_generated": "$20.98",
            "custom_event_21": "50.101",
            "custom_event_21_amount": "$256,194.77",
            "custom_event_22": "1",
            "ad_schedule": "",
            "m_avg_application_score": "61.544",
            "m_expected_roas": "32.85",
            "m_avg_expected_value": "$5,113.57"
          }
        }
      ]
    },
    "ads": {
      "headers": {
        "name": "Name",
        "delivery": "Delivery",
        "budget": "Budget",
        "amount_spent": "Amount Spent",
        "clicks": "Clicks (All)",
        "lead_generated": "Lead",
        "cost_per_lead_generated": "Cost per Lead",
        "custom_event_1": "Application Submitted",
        "cost_per_custom_event_1": "Cost per Application Submitted",
        "custom_event_20": "Application Score",
        "custom_event_21": "Application Expected Value",
        "custom_event_21_amount": "Application Expected Value Value",
        "custom_event_22": "Personal or Business Loan",
        "m_avg_application_score": "Avg Application Score",
        "m_expected_roas": "Expected ROAS",
        "m_avg_expected_value": "Avg Expected Value"
      },
      "rows": [
        {
          "id": "3377699811000897",
          "cells": {
            "ag-Grid-SelectionColumn": "",
            "name": "THMC_Meta_Generic_20260206",
            "_platform_url": "https://adsmanager.facebook.com/adsmanager/manage/campaigns?act=850448857515247&filter_set=SEARCH_BY_CAMPAIGN_GROUP_ID-STRING%1EEQUAL%1E%22120239432523620031%22&selected_campaign_ids=120239432523620031",
            "delivery": "Active",
            "budget": "Using Adset Budget",
            "amount_spent": "$4,244.18",
            "clicks": "2,519",
            "lead_generated": "257.458",
            "cost_per_lead_generated": "$16.48",
            "custom_event_1": "40.958",
            "cost_per_custom_event_1": "$103.62",
            "custom_event_20": "39.958",
            "custom_event_21": "39.958",
            "custom_event_21_amount": "$217,397.29",
            "custom_event_22": "1",
            "m_avg_application_score": "61.378",
            "m_expected_roas": "51.222",
            "m_avg_expected_value": "$5,440.63"
          }
        },
        {
          "id": "3377699818000368",
          "cells": {
            "ag-Grid-SelectionColumn": "",
            "name": "THMC_Meta_Generic_20260313",
            "_platform_url": "https://adsmanager.facebook.com/adsmanager/manage/campaigns?act=850448857515247&filter_set=SEARCH_BY_CAMPAIGN_GROUP_ID-STRING%1EEQUAL%1E%22120240918657590031%22&selected_campaign_ids=120240918657590031",
            "delivery": "Active",
            "budget": "Using Adset Budget",
            "amount_spent": "$1,191.17",
            "clicks": "318",
            "lead_generated": "34",
            "cost_per_lead_generated": "$35.03",
            "custom_event_1": "3.75",
            "cost_per_custom_event_1": "$317.65",
            "custom_event_20": "3.75",
            "custom_event_21": "3.75",
            "custom_event_21_amount": "$2,933.40",
            "custom_event_22": "-",
            "m_avg_application_score": "57.8",
            "m_expected_roas": "2.463",
            "m_avg_expected_value": "$782.24"
          }
        },
        {
          "id": "3377699820000065",
          "cells": {
            "ag-Grid-SelectionColumn": "",
            "name": "THMC_Meta_Generic_20260318_RIQ",
            "_platform_url": "https://adsmanager.facebook.com/adsmanager/manage/campaigns?act=850448857515247&filter_set=SEARCH_BY_CAMPAIGN_GROUP_ID-STRING%1EEQUAL%1E%22120241096252470031%22&selected_campaign_ids=120241096252470031",
            "delivery": "Active",
            "budget": "Using Adset Budget",
            "amount_spent": "$838.32",
            "clicks": "292",
            "lead_generated": "24.25",
            "cost_per_lead_generated": "$34.57",
            "custom_event_1": "2.25",
            "cost_per_custom_event_1": "$372.59",
            "custom_event_20": "2.25",
            "custom_event_21": "2.25",
            "custom_event_21_amount": "$3,593.50",
            "custom_event_22": "-",
            "m_avg_application_score": "67.667",
            "m_expected_roas": "4.287",
            "m_avg_expected_value": "$1,597.11"
          }
        },
        {
          "id": "4503599720000067",
          "cells": {
            "ag-Grid-SelectionColumn": "",
            "name": "THMC_Meta_Brokers_20260304 _Angle_Test",
            "_platform_url": "https://adsmanager.facebook.com/adsmanager/manage/campaigns?act=850448857515247&filter_set=SEARCH_BY_CAMPAIGN_GROUP_ID-STRING%1EEQUAL%1E%22120240548660790031%22&selected_campaign_ids=120240548660790031",
            "delivery": "Active",
            "budget": "Using Adset Budget",
            "amount_spent": "$1,505.42",
            "clicks": "421",
            "lead_generated": "55.833",
            "cost_per_lead_generated": "$26.96",
            "custom_event_1": "6",
            "cost_per_custom_event_1": "$250.90",
            "custom_event_20": "4",
            "custom_event_21": "4",
            "custom_event_21_amount": "$31,872.19",
            "custom_event_22": "-",
            "m_avg_application_score": "63.25",
            "m_expected_roas": "21.172",
            "m_avg_expected_value": "$7,968.05"
          }
        },
        {
          "id": "3377699808000188",
          "cells": {
            "ag-Grid-SelectionColumn": "",
            "name": "THMC_Meta_Forecasa&ForecasaADV+",
            "_platform_url": "https://adsmanager.facebook.com/adsmanager/manage/campaigns?act=850448857515247&filter_set=SEARCH_BY_CAMPAIGN_GROUP_ID-STRING%1EEQUAL%1E%22120238051629060031%22&selected_campaign_ids=120238051629060031",
            "delivery": "Paused",
            "budget": "$40.00\n(daily)",
            "amount_spent": "-",
            "clicks": "-",
            "lead_generated": "-",
            "cost_per_lead_generated": "-",
            "custom_event_1": "-",
            "cost_per_custom_event_1": "-",
            "custom_event_20": "-",
            "custom_event_21": "-",
            "custom_event_21_amount": "$0.00",
            "custom_event_22": "-",
            "m_avg_application_score": "-",
            "m_expected_roas": "-",
            "m_avg_expected_value": "-"
          }
        },
        {
          "id": "3377699808000368",
          "cells": {
            "ag-Grid-SelectionColumn": "",
            "name": "THMC_Meta_Milwaukee_20260106",
            "_platform_url": "https://adsmanager.facebook.com/adsmanager/manage/campaigns?act=850448857515247&filter_set=SEARCH_BY_CAMPAIGN_GROUP_ID-STRING%1EEQUAL%1E%22120238329184250031%22&selected_campaign_ids=120238329184250031",
            "delivery": "Paused",
            "budget": "$50.00\n(daily)",
            "amount_spent": "-",
            "clicks": "-",
            "lead_generated": "-",
            "cost_per_lead_generated": "-",
            "custom_event_1": "-",
            "cost_per_custom_event_1": "-",
            "custom_event_20": "-",
            "custom_event_21": "-",
            "custom_event_21_amount": "$0.00",
            "custom_event_22": "-",
            "m_avg_application_score": "-",
            "m_expected_roas": "-",
            "m_avg_expected_value": "-"
          }
        },
        {
          "id": "3377699818000367",
          "cells": {
            "ag-Grid-SelectionColumn": "",
            "name": "THMC_Meta_Generic_20251110_Copy_ABO",
            "_platform_url": "https://adsmanager.facebook.com/adsmanager/manage/campaigns?act=850448857515247&filter_set=SEARCH_BY_CAMPAIGN_GROUP_ID-STRING%1EEQUAL%1E%22120240919013850031%22&selected_campaign_ids=120240919013850031",
            "delivery": "Paused",
            "budget": "Using Adset Budget",
            "amount_spent": "$19.88",
            "clicks": "9",
            "lead_generated": "0.5",
            "cost_per_lead_generated": "$39.76",
            "custom_event_1": "-",
            "cost_per_custom_event_1": "-",
            "custom_event_20": "-",
            "custom_event_21": "-",
            "custom_event_21_amount": "-",
            "custom_event_22": "-",
            "m_avg_application_score": "-",
            "m_expected_roas": "-",
            "m_avg_expected_value": "-"
          }
        },
        {
          "id": "4503599706000234",
          "cells": {
            "ag-Grid-SelectionColumn": "",
            "name": "THMC_Meta_Generic_20251110",
            "_platform_url": "https://adsmanager.facebook.com/adsmanager/manage/campaigns?act=850448857515247&filter_set=SEARCH_BY_CAMPAIGN_GROUP_ID-STRING%1EEQUAL%1E%22120235243629020031%22&selected_campaign_ids=120235243629020031",
            "delivery": "Paused",
            "budget": "$315.00\n(daily)",
            "amount_spent": "-",
            "clicks": "-",
            "lead_generated": "0.667",
            "cost_per_lead_generated": "-",
            "custom_event_1": "0.143",
            "cost_per_custom_event_1": "-",
            "custom_event_20": "0.143",
            "custom_event_21": "0.143",
            "custom_event_21_amount": "$398.39",
            "custom_event_22": "-",
            "m_avg_application_score": "61.981",
            "m_expected_roas": "-",
            "m_avg_expected_value": "$2,787.89"
          }
        },
        {
          "id": "4503599713000291",
          "cells": {
            "ag-Grid-SelectionColumn": "",
            "name": "THMC_Meta_Generic_20251110 - Copy (RIQ Flippers)",
            "_platform_url": "https://adsmanager.facebook.com/adsmanager/manage/campaigns?act=850448857515247&filter_set=SEARCH_BY_CAMPAIGN_GROUP_ID-STRING%1EEQUAL%1E%22120238730003590031%22&selected_campaign_ids=120238730003590031",
            "delivery": "Paused",
            "budget": "$100.00\n(daily)",
            "amount_spent": "-",
            "clicks": "-",
            "lead_generated": "-",
            "cost_per_lead_generated": "-",
            "custom_event_1": "-",
            "cost_per_custom_event_1": "-",
            "custom_event_20": "-",
            "custom_event_21": "-",
            "custom_event_21_amount": "$0.00",
            "custom_event_22": "-",
            "m_avg_application_score": "-",
            "m_expected_roas": "-",
            "m_avg_expected_value": "-"
          }
        },
        {
          "id": "4503599713000335",
          "cells": {
            "ag-Grid-SelectionColumn": "",
            "name": "THMC_Meta_Brokers_20260106 - Copy(RIQAgents+LO's)",
            "_platform_url": "https://adsmanager.facebook.com/adsmanager/manage/campaigns?act=850448857515247&filter_set=SEARCH_BY_CAMPAIGN_GROUP_ID-STRING%1EEQUAL%1E%22120238771546440031%22&selected_campaign_ids=120238771546440031",
            "delivery": "Paused",
            "budget": "$100.00\n(daily)",
            "amount_spent": "-",
            "clicks": "-",
            "lead_generated": "-",
            "cost_per_lead_generated": "-",
            "custom_event_1": "-",
            "cost_per_custom_event_1": "-",
            "custom_event_20": "-",
            "custom_event_21": "-",
            "custom_event_21_amount": "$0.00",
            "custom_event_22": "-",
            "m_avg_application_score": "-",
            "m_expected_roas": "-",
            "m_avg_expected_value": "-"
          }
        },
        {
          "id": "Totals",
          "cells": {
            "ag-Grid-SelectionColumn": "",
            "name": "Totals",
            "delivery": "",
            "budget": "",
            "amount_spent": "$7,798.97",
            "clicks": "3,559",
            "lead_generated": "372.708",
            "cost_per_lead_generated": "$20.93",
            "custom_event_1": "53.101",
            "cost_per_custom_event_1": "$146.87",
            "custom_event_20": "50.101",
            "custom_event_21": "50.101",
            "custom_event_21_amount": "$256,194.77",
            "custom_event_22": "1",
            "m_avg_application_score": "61.544",
            "m_expected_roas": "32.85",
            "m_avg_expected_value": "$5,113.57"
          }
        }
      ]
    }
  },
  "google": {
    "campaigns": {
      "headers": {
        "name": "Name",
        "delivery": "Delivery",
        "budget": "Budget",
        "amount_spent": "Amount Spent",
        "clicks": "Clicks (All)",
        "lead_generated": "Lead",
        "cost_per_lead_generated": "Cost per Lead",
        "custom_event_1": "Application Submitted",
        "cost_per_custom_event_1": "Cost per Application Submitted",
        "custom_event_20": "Application Score",
        "custom_event_21": "Application Expected Value",
        "custom_event_21_amount": "Application Expected Value Value",
        "custom_event_22": "Personal or Business Loan",
        "m_avg_application_score": "Avg Application Score",
        "m_expected_roas": "Expected ROAS",
        "m_avg_expected_value": "Avg Expected Value"
      },
      "rows": [
        {
          "id": "3377699775000031",
          "cells": {
            "ag-Grid-SelectionColumn": "",
            "name": "THMC_Google_Remarketing All Markets",
            "delivery": "Active",
            "budget": "$360.00\n(daily)",
            "amount_spent": "$5,053.91",
            "clicks": "1,746",
            "lead_generated": "-",
            "cost_per_lead_generated": "-",
            "custom_event_1": "6.125",
            "cost_per_custom_event_1": "$825.13",
            "custom_event_20": "6.125",
            "custom_event_21": "5.125",
            "custom_event_21_amount": "$33,489.12",
            "custom_event_22": "4",
            "m_avg_application_score": "47.163",
            "m_expected_roas": "6.626",
            "m_avg_expected_value": "$6,534.46"
          }
        },
        {
          "id": "3377699775000036",
          "cells": {
            "ag-Grid-SelectionColumn": "",
            "name": "THMC_Google_Wisconsin | Brand | Search",
            "delivery": "Active",
            "budget": "$100.00\n(daily)",
            "amount_spent": "$1,458.13",
            "clicks": "61",
            "lead_generated": "0.375",
            "cost_per_lead_generated": "$3,888.35",
            "custom_event_1": "4.495",
            "cost_per_custom_event_1": "$324.41",
            "custom_event_20": "4.495",
            "custom_event_21": "4.495",
            "custom_event_21_amount": "$15,485.06",
            "custom_event_22": "-",
            "m_avg_application_score": "66.153",
            "m_expected_roas": "10.62",
            "m_avg_expected_value": "$3,445.18"
          }
        },
        {
          "id": "3377699775000037",
          "cells": {
            "ag-Grid-SelectionColumn": "",
            "name": "THMC_Google_Illinois Brand | Search",
            "delivery": "Active",
            "budget": "$100.00\n(daily)",
            "amount_spent": "$934.22",
            "clicks": "35",
            "lead_generated": "-",
            "cost_per_lead_generated": "-",
            "custom_event_1": "-",
            "cost_per_custom_event_1": "-",
            "custom_event_20": "-",
            "custom_event_21": "-",
            "custom_event_21_amount": "$0.00",
            "custom_event_22": "-",
            "m_avg_application_score": "-",
            "m_expected_roas": "-",
            "m_avg_expected_value": "-"
          }
        },
        {
          "id": "3377699775000038",
          "cells": {
            "ag-Grid-SelectionColumn": "",
            "name": "THMC_Google_Michigan | Brand | Search",
            "delivery": "Active",
            "budget": "$60.00\n(daily)",
            "amount_spent": "$280.32",
            "clicks": "24",
            "lead_generated": "-",
            "cost_per_lead_generated": "-",
            "custom_event_1": "2",
            "cost_per_custom_event_1": "$140.16",
            "custom_event_20": "2",
            "custom_event_21": "2",
            "custom_event_21_amount": "$8,207.81",
            "custom_event_22": "-",
            "m_avg_application_score": "72.5",
            "m_expected_roas": "29.28",
            "m_avg_expected_value": "$4,103.91"
          }
        },
        {
          "id": "3377699775000040",
          "cells": {
            "ag-Grid-SelectionColumn": "",
            "name": "THMC_Google_Expansion (FL, OH, NC) - Non-Brand Search",
            "delivery": "Active",
            "budget": "$400.00\n(daily)",
            "amount_spent": "$2,192.15",
            "clicks": "129",
            "lead_generated": "0.25",
            "cost_per_lead_generated": "$8,768.60",
            "custom_event_1": "5.411",
            "cost_per_custom_event_1": "$405.15",
            "custom_event_20": "5.411",
            "custom_event_21": "5.411",
            "custom_event_21_amount": "$9,593.11",
            "custom_event_22": "-",
            "m_avg_application_score": "62.023",
            "m_expected_roas": "4.376",
            "m_avg_expected_value": "$1,772.99"
          }
        },
        {
          "id": "3377699775000042",
          "cells": {
            "ag-Grid-SelectionColumn": "",
            "name": "THMC_Google_Core Markets (WI, MI, IL) - Non-Brand Search",
            "delivery": "Active",
            "budget": "$480.00\n(daily)",
            "amount_spent": "$10,429.55",
            "clicks": "383",
            "lead_generated": "0.792",
            "cost_per_lead_generated": "$13,175.28",
            "custom_event_1": "13.101",
            "cost_per_custom_event_1": "$796.08",
            "custom_event_20": "13.101",
            "custom_event_21": "11.101",
            "custom_event_21_amount": "$17,266.02",
            "custom_event_22": "5",
            "m_avg_application_score": "50",
            "m_expected_roas": "1.655",
            "m_avg_expected_value": "$1,555.33"
          }
        },
        {
          "id": "3377699805000023",
          "cells": {
            "ag-Grid-SelectionColumn": "",
            "name": "THMC_Google_US | Brand | Search",
            "delivery": "Active",
            "budget": "$700.00\n(daily)",
            "amount_spent": "$10,017.81",
            "clicks": "445",
            "lead_generated": "0.875",
            "cost_per_lead_generated": "$11,448.93",
            "custom_event_1": "18.768",
            "cost_per_custom_event_1": "$533.78",
            "custom_event_20": "18.768",
            "custom_event_21": "17.768",
            "custom_event_21_amount": "$140,428.81",
            "custom_event_22": "4",
            "m_avg_application_score": "56.732",
            "m_expected_roas": "14.018",
            "m_avg_expected_value": "$7,903.56"
          }
        },
        {
          "id": "3377699775000035",
          "cells": {
            "ag-Grid-SelectionColumn": "",
            "name": "Performance Max - Core Markets (WI, MI, IL)",
            "delivery": "Paused",
            "budget": "$200.00\n(daily)",
            "amount_spent": "-",
            "clicks": "-",
            "lead_generated": "-",
            "cost_per_lead_generated": "-",
            "custom_event_1": "-",
            "cost_per_custom_event_1": "-",
            "custom_event_20": "-",
            "custom_event_21": "-",
            "custom_event_21_amount": "$0.00",
            "custom_event_22": "-",
            "m_avg_application_score": "-",
            "m_expected_roas": "-",
            "m_avg_expected_value": "-"
          }
        },
        {
          "id": "3377699775000039",
          "cells": {
            "ag-Grid-SelectionColumn": "",
            "name": "THMC_Google_Demand Gen - All markets",
            "delivery": "Paused",
            "budget": "$160.00\n(daily)",
            "amount_spent": "-",
            "clicks": "-",
            "lead_generated": "-",
            "cost_per_lead_generated": "-",
            "custom_event_1": "-",
            "cost_per_custom_event_1": "-",
            "custom_event_20": "-",
            "custom_event_21": "-",
            "custom_event_21_amount": "$0.00",
            "custom_event_22": "-",
            "m_avg_application_score": "-",
            "m_expected_roas": "-",
            "m_avg_expected_value": "-"
          }
        },
        {
          "id": "4503599712000010",
          "cells": {
            "ag-Grid-SelectionColumn": "",
            "name": "THMC_Google_DemandGen_Forecasa",
            "delivery": "Paused",
            "budget": "$100.00\n(daily)",
            "amount_spent": "-",
            "clicks": "-",
            "lead_generated": "-",
            "cost_per_lead_generated": "-",
            "custom_event_1": "-",
            "cost_per_custom_event_1": "-",
            "custom_event_20": "-",
            "custom_event_21": "-",
            "custom_event_21_amount": "$0.00",
            "custom_event_22": "-",
            "m_avg_application_score": "-",
            "m_expected_roas": "-",
            "m_avg_expected_value": "-"
          }
        },
        {
          "id": "Totals",
          "cells": {
            "ag-Grid-SelectionColumn": "",
            "name": "Totals",
            "delivery": "",
            "budget": "",
            "amount_spent": "$30,366.09",
            "clicks": "2,823",
            "lead_generated": "2.292",
            "cost_per_lead_generated": "$13,251.04",
            "custom_event_1": "49.899",
            "cost_per_custom_event_1": "$608.55",
            "custom_event_20": "49.899",
            "custom_event_21": "45.899",
            "custom_event_21_amount": "$224,469.92",
            "custom_event_22": "13",
            "m_avg_application_score": "55.844",
            "m_expected_roas": "7.392",
            "m_avg_expected_value": "$4,890.48"
          }
        }
      ]
    },
    "adsets": {
      "headers": {
        "name": "Name",
        "custom_event_1": "Application Submitted",
        "cost_per_custom_event_1": "Cost per Application Submitted",
        "custom_event_20": "Application Score",
        "delivery": "Delivery",
        "amount_spent": "Amount Spent",
        "clicks": "Clicks (All)",
        "lead_generated": "Lead",
        "cost_per_lead_generated": "Cost per Lead",
        "custom_event_21": "Application Expected Value",
        "custom_event_21_amount": "Application Expected Value Value",
        "custom_event_22": "Personal or Business Loan",
        "m_avg_application_score": "Avg Application Score",
        "m_expected_roas": "Expected ROAS",
        "m_avg_expected_value": "Avg Expected Value"
      },
      "rows": [
        {
          "id": "4503599682000035",
          "cells": {
            "ag-Grid-SelectionColumn": "",
            "name": "THMC_Google_Remarketing_AllUsers",
            "delivery": "Active",
            "amount_spent": "$5,053.91",
            "clicks": "1,746",
            "lead_generated": "-",
            "cost_per_lead_generated": "-",
            "custom_event_1": "6.125",
            "cost_per_custom_event_1": "$825.13",
            "custom_event_20": "6.125",
            "custom_event_21": "5.125",
            "custom_event_21_amount": "$33,489.12",
            "custom_event_22": "4",
            "m_avg_application_score": "47.163",
            "m_expected_roas": "6.626",
            "m_avg_expected_value": "$6,534.46"
          }
        },
        {
          "id": "4503599682000036",
          "cells": {
            "ag-Grid-SelectionColumn": "",
            "name": "THMC_Google_Wisconsin_Brand_Search",
            "delivery": "Active",
            "amount_spent": "$1,458.13",
            "clicks": "61",
            "lead_generated": "0.375",
            "cost_per_lead_generated": "$3,888.35",
            "custom_event_1": "4.495",
            "cost_per_custom_event_1": "$324.41",
            "custom_event_20": "4.495",
            "custom_event_21": "4.495",
            "custom_event_21_amount": "$15,485.06",
            "custom_event_22": "-",
            "m_avg_application_score": "66.153",
            "m_expected_roas": "10.62",
            "m_avg_expected_value": "$3,445.18"
          }
        },
        {
          "id": "4503599682000037",
          "cells": {
            "ag-Grid-SelectionColumn": "",
            "name": "THMC_Google_Illinois_Brand_Search",
            "delivery": "Active",
            "amount_spent": "$934.22",
            "clicks": "35",
            "lead_generated": "-",
            "cost_per_lead_generated": "-",
            "custom_event_1": "-",
            "cost_per_custom_event_1": "-",
            "custom_event_20": "-",
            "custom_event_21": "-",
            "custom_event_21_amount": "$0.00",
            "custom_event_22": "-",
            "m_avg_application_score": "-",
            "m_expected_roas": "-",
            "m_avg_expected_value": "-"
          }
        },
        {
          "id": "4503599682000038",
          "cells": {
            "ag-Grid-SelectionColumn": "",
            "name": "THMC_Google_Michigan_Brand_Search",
            "delivery": "Active",
            "amount_spent": "$280.32",
            "clicks": "24",
            "lead_generated": "-",
            "cost_per_lead_generated": "-",
            "custom_event_1": "2",
            "cost_per_custom_event_1": "$140.16",
            "custom_event_20": "2",
            "custom_event_21": "2",
            "custom_event_21_amount": "$8,207.81",
            "custom_event_22": "-",
            "m_avg_application_score": "72.5",
            "m_expected_roas": "29.28",
            "m_avg_expected_value": "$4,103.91"
          }
        },
        {
          "id": "4503599682000040",
          "cells": {
            "ag-Grid-SelectionColumn": "",
            "name": "Fix & Flip Interest + Similar Site Visitors + App Usage",
            "delivery": "Active",
            "amount_spent": "-",
            "clicks": "-",
            "lead_generated": "-",
            "cost_per_lead_generated": "-",
            "custom_event_1": "-",
            "cost_per_custom_event_1": "-",
            "custom_event_20": "-",
            "custom_event_21": "-",
            "custom_event_21_amount": "$0.00",
            "custom_event_22": "-",
            "m_avg_application_score": "-",
            "m_expected_roas": "-",
            "m_avg_expected_value": "-"
          }
        },
        {
          "id": "4503599682000041",
          "cells": {
            "ag-Grid-SelectionColumn": "",
            "name": "THMC_Google_CoreMarkets_NonBrand_Search",
            "delivery": "Active",
            "amount_spent": "$10,429.55",
            "clicks": "383",
            "lead_generated": "0.792",
            "cost_per_lead_generated": "$13,175.28",
            "custom_event_1": "13.101",
            "cost_per_custom_event_1": "$796.08",
            "custom_event_20": "13.101",
            "custom_event_21": "11.101",
            "custom_event_21_amount": "$17,266.02",
            "custom_event_22": "5",
            "m_avg_application_score": "50",
            "m_expected_roas": "1.655",
            "m_avg_expected_value": "$1,555.33"
          }
        },
        {
          "id": "4503599682000050",
          "cells": {
            "ag-Grid-SelectionColumn": "",
            "name": "THMC_Google_Expansion_NonBrand_Search",
            "delivery": "Active",
            "amount_spent": "$2,192.15",
            "clicks": "129",
            "lead_generated": "0.25",
            "cost_per_lead_generated": "$8,768.60",
            "custom_event_1": "5.411",
            "cost_per_custom_event_1": "$405.15",
            "custom_event_20": "5.411",
            "custom_event_21": "5.411",
            "custom_event_21_amount": "$9,593.11",
            "custom_event_22": "-",
            "m_avg_application_score": "62.023",
            "m_expected_roas": "4.376",
            "m_avg_expected_value": "$1,772.99"
          }
        },
        {
          "id": "4503599712000017",
          "cells": {
            "ag-Grid-SelectionColumn": "",
            "name": "Forecasa",
            "delivery": "Active",
            "amount_spent": "-",
            "clicks": "-",
            "lead_generated": "-",
            "cost_per_lead_generated": "-",
            "custom_event_1": "-",
            "cost_per_custom_event_1": "-",
            "custom_event_20": "-",
            "custom_event_21": "-",
            "custom_event_21_amount": "$0.00",
            "custom_event_22": "-",
            "m_avg_application_score": "-",
            "m_expected_roas": "-",
            "m_avg_expected_value": "-"
          }
        },
        {
          "id": "4503599712000062",
          "cells": {
            "ag-Grid-SelectionColumn": "",
            "name": "THMC_Google_US_Brand_Search",
            "delivery": "Active",
            "amount_spent": "$10,017.81",
            "clicks": "445",
            "lead_generated": "0.875",
            "cost_per_lead_generated": "$11,448.93",
            "custom_event_1": "18.768",
            "cost_per_custom_event_1": "$533.78",
            "custom_event_20": "18.768",
            "custom_event_21": "17.768",
            "custom_event_21_amount": "$140,428.81",
            "custom_event_22": "4",
            "m_avg_application_score": "56.732",
            "m_expected_roas": "14.018",
            "m_avg_expected_value": "$7,903.56"
          }
        },
        {
          "id": "4503599682000033",
          "cells": {
            "ag-Grid-SelectionColumn": "",
            "name": "Performance Max - Core Markets (WI, MI, IL) (performance_max)",
            "delivery": "Paused",
            "amount_spent": "-",
            "clicks": "-",
            "lead_generated": "-",
            "cost_per_lead_generated": "-",
            "custom_event_1": "-",
            "cost_per_custom_event_1": "-",
            "custom_event_20": "-",
            "custom_event_21": "-",
            "custom_event_21_amount": "$0.00",
            "custom_event_22": "-",
            "m_avg_application_score": "-",
            "m_expected_roas": "-",
            "m_avg_expected_value": "-"
          }
        },
        {
          "id": "Totals",
          "cells": {
            "ag-Grid-SelectionColumn": "",
            "name": "Totals",
            "custom_event_1": "49.899",
            "cost_per_custom_event_1": "$608.55",
            "custom_event_20": "49.899",
            "delivery": "",
            "amount_spent": "$30,366.09",
            "clicks": "2,823",
            "lead_generated": "2.292",
            "cost_per_lead_generated": "$13,251.04",
            "custom_event_21": "45.899",
            "custom_event_21_amount": "$224,469.92",
            "custom_event_22": "13",
            "m_avg_application_score": "55.844",
            "m_expected_roas": "7.392",
            "m_avg_expected_value": "$4,890.48"
          }
        }
      ]
    },
    "ads": {
      "headers": {
        "name": "Name",
        "delivery": "Delivery",
        "amount_spent": "Amount Spent",
        "clicks": "Clicks (All)",
        "lead_generated": "Lead",
        "cost_per_lead_generated": "Cost per Lead",
        "custom_event_1": "Application Submitted",
        "cost_per_custom_event_1": "Cost per Application Submitted",
        "custom_event_20": "Application Score",
        "budget": "Budget",
        "custom_event_21": "Application Expected Value",
        "custom_event_21_amount": "Application Expected Value Value",
        "custom_event_22": "Personal or Business Loan",
        "m_avg_application_score": "Avg Application Score",
        "m_expected_roas": "Expected ROAS",
        "m_avg_expected_value": "Avg Expected Value"
      },
      "rows": [
        {
          "id": "3377699811000897",
          "cells": {
            "ag-Grid-SelectionColumn": "",
            "name": "THMC_Meta_Generic_20260206",
            "_platform_url": "https://adsmanager.facebook.com/adsmanager/manage/campaigns?act=850448857515247&filter_set=SEARCH_BY_CAMPAIGN_GROUP_ID-STRING%1EEQUAL%1E%22120239432523620031%22&selected_campaign_ids=120239432523620031",
            "budget": "Using Adset Budget",
            "amount_spent": "$4,244.18",
            "clicks": "2,519",
            "lead_generated": "257.458",
            "cost_per_lead_generated": "$16.48",
            "custom_event_1": "40.958",
            "cost_per_custom_event_1": "$103.62",
            "custom_event_20": "39.958",
            "custom_event_21": "39.958",
            "custom_event_21_amount": "$217,397.29",
            "custom_event_22": "1",
            "m_avg_application_score": "61.378",
            "m_expected_roas": "51.222",
            "m_avg_expected_value": "$5,440.63"
          }
        },
        {
          "id": "3377699818000368",
          "cells": {
            "ag-Grid-SelectionColumn": "",
            "name": "THMC_Meta_Generic_20260313",
            "_platform_url": "https://adsmanager.facebook.com/adsmanager/manage/campaigns?act=850448857515247&filter_set=SEARCH_BY_CAMPAIGN_GROUP_ID-STRING%1EEQUAL%1E%22120240918657590031%22&selected_campaign_ids=120240918657590031",
            "budget": "Using Adset Budget",
            "amount_spent": "$1,191.17",
            "clicks": "318",
            "lead_generated": "34",
            "cost_per_lead_generated": "$35.03",
            "custom_event_1": "3.75",
            "cost_per_custom_event_1": "$317.65",
            "custom_event_20": "3.75",
            "custom_event_21": "3.75",
            "custom_event_21_amount": "$2,933.40",
            "custom_event_22": "-",
            "m_avg_application_score": "57.8",
            "m_expected_roas": "2.463",
            "m_avg_expected_value": "$782.24"
          }
        },
        {
          "id": "3377699820000065",
          "cells": {
            "ag-Grid-SelectionColumn": "",
            "name": "THMC_Meta_Generic_20260318_RIQ",
            "_platform_url": "https://adsmanager.facebook.com/adsmanager/manage/campaigns?act=850448857515247&filter_set=SEARCH_BY_CAMPAIGN_GROUP_ID-STRING%1EEQUAL%1E%22120241096252470031%22&selected_campaign_ids=120241096252470031",
            "budget": "Using Adset Budget",
            "amount_spent": "$838.32",
            "clicks": "292",
            "lead_generated": "24.25",
            "cost_per_lead_generated": "$34.57",
            "custom_event_1": "2.25",
            "cost_per_custom_event_1": "$372.59",
            "custom_event_20": "2.25",
            "custom_event_21": "2.25",
            "custom_event_21_amount": "$3,593.50",
            "custom_event_22": "-",
            "m_avg_application_score": "67.667",
            "m_expected_roas": "4.287",
            "m_avg_expected_value": "$1,597.11"
          }
        },
        {
          "id": "4503599720000067",
          "cells": {
            "ag-Grid-SelectionColumn": "",
            "name": "THMC_Meta_Brokers_20260304 _Angle_Test",
            "_platform_url": "https://adsmanager.facebook.com/adsmanager/manage/campaigns?act=850448857515247&filter_set=SEARCH_BY_CAMPAIGN_GROUP_ID-STRING%1EEQUAL%1E%22120240548660790031%22&selected_campaign_ids=120240548660790031",
            "budget": "Using Adset Budget",
            "amount_spent": "$1,505.42",
            "clicks": "421",
            "lead_generated": "55.833",
            "cost_per_lead_generated": "$26.96",
            "custom_event_1": "6",
            "cost_per_custom_event_1": "$250.90",
            "custom_event_20": "4",
            "custom_event_21": "4",
            "custom_event_21_amount": "$31,872.19",
            "custom_event_22": "-",
            "m_avg_application_score": "63.25",
            "m_expected_roas": "21.172",
            "m_avg_expected_value": "$7,968.05"
          }
        },
        {
          "id": "3377699808000188",
          "cells": {
            "ag-Grid-SelectionColumn": "",
            "name": "THMC_Meta_Forecasa&ForecasaADV+",
            "_platform_url": "https://adsmanager.facebook.com/adsmanager/manage/campaigns?act=850448857515247&filter_set=SEARCH_BY_CAMPAIGN_GROUP_ID-STRING%1EEQUAL%1E%22120238051629060031%22&selected_campaign_ids=120238051629060031",
            "budget": "$40.00\n(daily)",
            "amount_spent": "-",
            "clicks": "-",
            "lead_generated": "-",
            "cost_per_lead_generated": "-",
            "custom_event_1": "-",
            "cost_per_custom_event_1": "-",
            "custom_event_20": "-",
            "custom_event_21": "-",
            "custom_event_21_amount": "$0.00",
            "custom_event_22": "-",
            "m_avg_application_score": "-",
            "m_expected_roas": "-",
            "m_avg_expected_value": "-"
          }
        },
        {
          "id": "3377699808000368",
          "cells": {
            "ag-Grid-SelectionColumn": "",
            "name": "THMC_Meta_Milwaukee_20260106",
            "_platform_url": "https://adsmanager.facebook.com/adsmanager/manage/campaigns?act=850448857515247&filter_set=SEARCH_BY_CAMPAIGN_GROUP_ID-STRING%1EEQUAL%1E%22120238329184250031%22&selected_campaign_ids=120238329184250031",
            "budget": "$50.00\n(daily)",
            "amount_spent": "-",
            "clicks": "-",
            "lead_generated": "-",
            "cost_per_lead_generated": "-",
            "custom_event_1": "-",
            "cost_per_custom_event_1": "-",
            "custom_event_20": "-",
            "custom_event_21": "-",
            "custom_event_21_amount": "$0.00",
            "custom_event_22": "-",
            "m_avg_application_score": "-",
            "m_expected_roas": "-",
            "m_avg_expected_value": "-"
          }
        },
        {
          "id": "3377699818000367",
          "cells": {
            "ag-Grid-SelectionColumn": "",
            "name": "THMC_Meta_Generic_20251110_Copy_ABO",
            "_platform_url": "https://adsmanager.facebook.com/adsmanager/manage/campaigns?act=850448857515247&filter_set=SEARCH_BY_CAMPAIGN_GROUP_ID-STRING%1EEQUAL%1E%22120240919013850031%22&selected_campaign_ids=120240919013850031",
            "budget": "Using Adset Budget",
            "amount_spent": "$19.88",
            "clicks": "9",
            "lead_generated": "0.5",
            "cost_per_lead_generated": "$39.76",
            "custom_event_1": "-",
            "cost_per_custom_event_1": "-",
            "custom_event_20": "-",
            "custom_event_21": "-",
            "custom_event_21_amount": "-",
            "custom_event_22": "-",
            "m_avg_application_score": "-",
            "m_expected_roas": "-",
            "m_avg_expected_value": "-"
          }
        },
        {
          "id": "4503599706000234",
          "cells": {
            "ag-Grid-SelectionColumn": "",
            "name": "THMC_Meta_Generic_20251110",
            "_platform_url": "https://adsmanager.facebook.com/adsmanager/manage/campaigns?act=850448857515247&filter_set=SEARCH_BY_CAMPAIGN_GROUP_ID-STRING%1EEQUAL%1E%22120235243629020031%22&selected_campaign_ids=120235243629020031",
            "budget": "$315.00\n(daily)",
            "amount_spent": "-",
            "clicks": "-",
            "lead_generated": "0.667",
            "cost_per_lead_generated": "-",
            "custom_event_1": "0.143",
            "cost_per_custom_event_1": "-",
            "custom_event_20": "0.143",
            "custom_event_21": "0.143",
            "custom_event_21_amount": "$398.39",
            "custom_event_22": "-",
            "m_avg_application_score": "61.981",
            "m_expected_roas": "-",
            "m_avg_expected_value": "$2,787.89"
          }
        },
        {
          "id": "4503599713000291",
          "cells": {
            "ag-Grid-SelectionColumn": "",
            "name": "THMC_Meta_Generic_20251110 - Copy (RIQ Flippers)",
            "_platform_url": "https://adsmanager.facebook.com/adsmanager/manage/campaigns?act=850448857515247&filter_set=SEARCH_BY_CAMPAIGN_GROUP_ID-STRING%1EEQUAL%1E%22120238730003590031%22&selected_campaign_ids=120238730003590031",
            "budget": "$100.00\n(daily)",
            "amount_spent": "-",
            "clicks": "-",
            "lead_generated": "-",
            "cost_per_lead_generated": "-",
            "custom_event_1": "-",
            "cost_per_custom_event_1": "-",
            "custom_event_20": "-",
            "custom_event_21": "-",
            "custom_event_21_amount": "$0.00",
            "custom_event_22": "-",
            "m_avg_application_score": "-",
            "m_expected_roas": "-",
            "m_avg_expected_value": "-"
          }
        },
        {
          "id": "4503599713000335",
          "cells": {
            "ag-Grid-SelectionColumn": "",
            "name": "THMC_Meta_Brokers_20260106 - Copy(RIQAgents+LO's)",
            "_platform_url": "https://adsmanager.facebook.com/adsmanager/manage/campaigns?act=850448857515247&filter_set=SEARCH_BY_CAMPAIGN_GROUP_ID-STRING%1EEQUAL%1E%22120238771546440031%22&selected_campaign_ids=120238771546440031",
            "budget": "$100.00\n(daily)",
            "amount_spent": "-",
            "clicks": "-",
            "lead_generated": "-",
            "cost_per_lead_generated": "-",
            "custom_event_1": "-",
            "cost_per_custom_event_1": "-",
            "custom_event_20": "-",
            "custom_event_21": "-",
            "custom_event_21_amount": "$0.00",
            "custom_event_22": "-",
            "m_avg_application_score": "-",
            "m_expected_roas": "-",
            "m_avg_expected_value": "-"
          }
        },
        {
          "id": "Totals",
          "cells": {
            "ag-Grid-SelectionColumn": "",
            "name": "Totals",
            "budget": "",
            "amount_spent": "$7,798.97",
            "clicks": "3,559",
            "lead_generated": "372.708",
            "cost_per_lead_generated": "$20.93",
            "custom_event_1": "53.101",
            "cost_per_custom_event_1": "$146.87",
            "custom_event_20": "50.101",
            "custom_event_21": "50.101",
            "custom_event_21_amount": "$256,194.77",
            "custom_event_22": "1",
            "m_avg_application_score": "61.544",
            "m_expected_roas": "32.85",
            "m_avg_expected_value": "$5,113.57"
          }
        }
      ]
    }
  }
}